{
    "Git_Configuration":  [
                              {
                                  "git_username":  null,
                                  "git_provider":  "gitHub"
                              }
                          ],
    "Repo_Configuration":  [
                               {
                                   "url":  null,
                                   "provider":  "gitHub",
                                   "path":  "UATFolder",
                                   "branch":  "main"
                               }
                           ]
}